{
  "beat_number": 0,
  "timestamp_utc": "2025-12-13T15:04:38.158561+00:00",
  "timestamp_local": "2025-12-13T15:04:38.158569",
  "backend_name": "ibm_fez",
  "job_id": "d4uo10cgk3fc73au61e0",
  "execution_time_seconds": 4.958827495574951,
  "source": "real",
  "backend_family": "heron",
  "backend_processor": "r1",
  "num_qubits": 5,
  "circuit_depth": 8,
  "shots": 1024,
  "counts": {
    "01100": 11,
    "00000": 747,
    "00001": 38,
    "10000": 52,
    "00010": 37,
    "01000": 47,
    "11000": 18,
    "00100": 38,
    "10100": 8,
    "10010": 2,
    "00011": 11,
    "00111": 2,
    "00110": 4,
    "11100": 3,
    "01001": 3,
    "01110": 1,
    "11010": 1,
    "00101": 1
  },
  "coherence_estimate": 0.7294921875,
  "entropy": 0.34456149241093,
  "top_states": [
    {
      "state": "00000",
      "count": 747,
      "probability": 0.7294921875
    },
    {
      "state": "10000",
      "count": 52,
      "probability": 0.05078125
    },
    {
      "state": "01000",
      "count": 47,
      "probability": 0.0458984375
    },
    {
      "state": "00001",
      "count": 38,
      "probability": 0.037109375
    },
    {
      "state": "00100",
      "count": 38,
      "probability": 0.037109375
    }
  ],
  "budget_used_total": 4.958827495574951,
  "budget_remaining": 595.041172504425
}